pyregion/_region_filter.c
pyregion/conftest.py
pyregion/version.py
pyregion/region_numbers.py
pyregion/_region_filter.cpython-312-darwin.so
pyregion/region_to_filter.py
pyregion/__init__.py
pyregion/core.py
pyregion/ds9_region_parser.py
pyregion/parser_helper.py
pyregion/compiler_version.cpython-312-darwin.so
pyregion/_region_filter.pyx
pyregion/_compiler.c
pyregion/wcs_helper.py
pyregion/c_numpy.pxd
pyregion/c_python.pxd
pyregion/mpl_helper.py
pyregion/ds9_attr_parser.py
pyregion/physical_coordinate.py
pyregion/setup_package.py
pyregion/geom.h
pyregion/wcs_converter.py
pyregion/tests/test_ds9_attr_parser.py
pyregion/tests/test_cube.py
pyregion/tests/test_region_numbers.py
pyregion/tests/coveragerc
pyregion/tests/test_parser_helper.py
pyregion/tests/test_region.py
pyregion/tests/test_get_mask.py
pyregion/tests/test_wcs.py
pyregion/tests/test_ds9_region_parser.py
pyregion/tests/data/test01_ds9_physical.reg
pyregion/tests/data/test_text.reg
pyregion/tests/data/test02_1_fk5.reg
pyregion/tests/data/sample_fits03.header
pyregion/tests/data/test01_gal.reg
pyregion/tests/data/test_annuli.reg
pyregion/tests/data/sample_fits01.header
pyregion/tests/data/test01_fk5_degree.reg
pyregion/tests/data/test01_img.reg
pyregion/tests/data/test01_ciao_physical.reg
pyregion/tests/data/test_annuli_wcs.reg
pyregion/tests/data/test03_img.reg
pyregion/tests/data/test.header
pyregion/tests/data/test_annuli_ciao.reg
pyregion/tests/data/test02.reg
pyregion/tests/data/test03_icrs.reg
pyregion/tests/data/test01.reg
pyregion/tests/data/test03_ciao_physical.reg
pyregion/tests/data/test03_gal.reg
pyregion/tests/data/sample_fits02.header
pyregion/tests/data/test03_fk5.reg
pyregion/tests/data/test_context.reg
pyregion/tests/data/test02_1_img.reg
pyregion/tests/data/test04_img.reg
pyregion/tests/data/sample_fits04.header
pyregion/tests/data/test01_fk5_sexagecimal.reg
pyregion/tests/data/test01_ciao.reg
pyregion/tests/data/test01_icrs.reg
pyregion-2.3.0.dist-info/RECORD
pyregion-2.3.0.dist-info/LICENSE
pyregion-2.3.0.dist-info/WHEEL
pyregion-2.3.0.dist-info/top_level.txt
pyregion-2.3.0.dist-info/METADATA
