Metadata-Version: 2.1
Name: pyregion
Version: 2.3.0
Summary: python parser for ds9 region files
Author-email: Jae-Joon Lee <lee.j.joon@gmail.com>
License: MIT
Project-URL: Documentation, https://pyregion.readthedocs.io/
Project-URL: Homepage, https://github.com/astropy/pyregion
Project-URL: Source, https://github.com/astropy/pyregion
Project-URL: Tracker, https://github.com/astropy/pyregion/issues
Classifier: Programming Language :: Python :: 3 :: Only
Classifier: Programming Language :: Python :: 3.10
Classifier: Programming Language :: Python :: 3.11
Classifier: Programming Language :: Python :: 3.12
Classifier: Topic :: Scientific/Engineering :: Astronomy
Requires-Python: >=3.10
License-File: LICENSE
Requires-Dist: astropy >=5
Requires-Dist: numpy >=1.23
Requires-Dist: pyparsing >=2
Provides-Extra: docs
Requires-Dist: matplotlib ; extra == 'docs'
Requires-Dist: sphinx ; extra == 'docs'
Requires-Dist: sphinx-astropy ; extra == 'docs'
Requires-Dist: sphinx-rtd-theme ; extra == 'docs'
Provides-Extra: test
Requires-Dist: pytest ; extra == 'test'
Requires-Dist: pytest-astropy ; extra == 'test'
